rte_sonar_reports/RTE_logo.svg
rte_sonar_reports/__init__.py
rte_sonar_reports/__main__.py
rte_sonar_reports/app.py
rte_sonar_reports/application_description_schema.yml
rte_sonar_reports/loaders.py
rte_sonar_reports/pdf.py
rte_sonar_reports/prescription_validator.py
rte_sonar_reports/sonar.py
rte_sonar_reports/traffic_green.svg
rte_sonar_reports/traffic_orange.svg
rte_sonar_reports/traffic_red.svg
rte_sonar_reports-2025.3.1.dist-info/licenses/LICENSE
rte_sonar_reports-2025.3.1.dist-info/METADATA
rte_sonar_reports-2025.3.1.dist-info/WHEEL
rte_sonar_reports-2025.3.1.dist-info/entry_points.txt
rte_sonar_reports-2025.3.1.dist-info/top_level.txt
rte_sonar_reports-2025.3.1.dist-info/RECORD
