Metadata-Version: 2.4
Name: rte-sonar-reports
Version: 2025.3.1
Summary: Tools for generating PDF reports used as requirements for deployment of an application in RTE production environments
Maintainer-email: Sebastien MURGEY <sebastien.murgey@rte-france.com>
License: Mozilla Public License Version 2.0
Project-URL: Homepage, https://github.com/rte-france/rte-sonar-report
Project-URL: Issues, https://github.com/rte-france/rte-sonar-report/issues
Classifier: Programming Language :: Python :: 3
Requires-Python: >=3.9
License-File: LICENSE
Requires-Dist: ordered-enum
Requires-Dist: pyyml
Requires-Dist: importlib_resources
Requires-Dist: jsonschema
Requires-Dist: requests
Requires-Dist: reportlab
Requires-Dist: svglib==1.5.1
Requires-Dist: pytz
Provides-Extra: dev
Requires-Dist: pytest; extra == "dev"
Requires-Dist: requests-mock; extra == "dev"
Requires-Dist: pdf2image; extra == "dev"
Dynamic: license-file
